yt_ex/__init__.py
yt_ex/extractors.py
yt_ex/objs.py
yt_ex/yt_ex.py
yt_ex-0.0.3.dist-info/METADATA
yt_ex-0.0.3.dist-info/WHEEL
yt_ex-0.0.3.dist-info/entry_points.txt
yt_ex-0.0.3.dist-info/licenses/LICENSE
yt_ex-0.0.3.dist-info/RECORD
