Metadata-Version: 2.4
Name: yt-ex
Version: 0.0.3
Summary: Scripts for extracting data provided by Google's private InnerTube API. 
License: GNU General Public License v3 (GPLv3)
License-File: LICENSE
Author: Simone Gentili
Author-email: gensimone.git@gmail.com
Requires-Python: >=3.12,<4.0
Classifier: License :: Other/Proprietary License
Classifier: Programming Language :: Python :: 3
Classifier: Programming Language :: Python :: 3.12
Classifier: Programming Language :: Python :: 3.13
Classifier: Programming Language :: Python :: 3.14
Requires-Dist: innertube
